{
  "fill-specializations" : [
    {
      "value" : {
        "automatic-gradient" : "gray:1.00000,1.00000"
      }
    },
    {
      "appearance" : "dark",
      "value" : "automatic"
    }
  ],
  "groups" : [
    {
      "hidden-specializations" : [
        {
          "value" : false
        },
        {
          "idiom" : "square",
          "value" : true
        }
      ],
      "layers" : [
        {
          "image-name" : "beta2.png",
          "name" : "beta2",
          "position" : {
            "scale" : 1,
            "translation-in-points" : [
              -329.4375,
              -351.6484375
            ]
          }
        },
        {
          "fill" : "automatic",
          "image-name" : "bear2.png",
          "name" : "bear2",
          "position" : {
            "scale" : 1,
            "translation-in-points" : [
              165.7734375,
              105.328125
            ]
          }
        }
      ],
      "shadow" : {
        "kind" : "neutral",
        "opacity" : 0.5
      },
      "translucency" : {
        "enabled" : true,
        "value" : 0.5
      }
    },
    {
      "blend-mode-specializations" : [
        {
          "appearance" : "dark",
          "value" : "normal"
        }
      ],
      "hidden-specializations" : [
        {
          "idiom" : "watchOS",
          "value" : true
        }
      ],
      "layers" : [
        {
          "image-name" : "beta1.png",
          "name" : "beta1"
        },
        {
          "blend-mode-specializations" : [
            {
              "appearance" : "tinted",
              "value" : "hard-light"
            }
          ],
          "fill-specializations" : [
            {
              "value" : "automatic"
            },
            {
              "appearance" : "dark",
              "value" : {
                "solid" : "srgb:1.00000,1.00000,1.00000,1.00000"
              }
            },
            {
              "appearance" : "tinted",
              "value" : {
                "solid" : "gray:1.00000,1.00000"
              }
            }
          ],
          "glass" : true,
          "image-name" : "bear1.png",
          "name" : "bear1",
          "opacity-specializations" : [
            {
              "appearance" : "dark",
              "value" : 0.9
            },
            {
              "appearance" : "tinted",
              "value" : 0.41
            }
          ],
          "position" : {
            "scale" : 1,
            "translation-in-points" : [
              0.9850330965443601,
              7.408558782460398
            ]
          }
        }
      ],
      "shadow" : {
        "kind" : "neutral",
        "opacity" : 0.5
      },
      "specular" : true,
      "translucency" : {
        "enabled" : true,
        "value" : 0.5
      }
    }
  ],
  "supported-platforms" : {
    "squares" : "shared"
  }
}